ascii_tee/__init__.py
ascii_tee/api.py
ascii_tee/cli.py
ascii_tee/display.py
ascii_tee/models.py
ascii_tee/preview.py
ascii_tee/assets/black.jpg
ascii_tee/assets/white.jpg
ascii_tee-0.1.1.dist-info/METADATA
ascii_tee-0.1.1.dist-info/WHEEL
ascii_tee-0.1.1.dist-info/entry_points.txt
ascii_tee-0.1.1.dist-info/licenses/LICENSE
ascii_tee-0.1.1.dist-info/RECORD
