Metadata-Version: 2.4
Name: ascii-tee
Version: 0.1.1
Summary: Generate custom ASCII art t-shirts from the command line
Project-URL: Homepage, https://github.com/cdinnison/ascii-tee
Project-URL: Repository, https://github.com/cdinnison/ascii-tee
Author: Clark Developer
License-Expression: MIT
License-File: LICENSE
Keywords: art,ascii,cli,generator,tshirt
Classifier: Development Status :: 4 - Beta
Classifier: Environment :: Console
Classifier: Intended Audience :: End Users/Desktop
Classifier: License :: OSI Approved :: MIT License
Classifier: Programming Language :: Python :: 3
Classifier: Programming Language :: Python :: 3.11
Classifier: Programming Language :: Python :: 3.12
Classifier: Programming Language :: Python :: 3.13
Classifier: Topic :: Artistic Software
Requires-Python: >=3.11
Requires-Dist: httpx>=0.27.0
Requires-Dist: pillow>=10.0.0
Requires-Dist: pydantic>=2.0.0
Requires-Dist: rich>=13.0.0
Requires-Dist: typer>=0.12.0
